netcore/__init__.py
netcore/blueprint.py
netcore/cache.py
netcore/endpoint.py
netcore/error.py
netcore/event.py
netcore/lso.py
netcore/scheduler.py
netcore-0.1.3.dist-info/licenses/LICENSE
netcore-0.1.3.dist-info/METADATA
netcore-0.1.3.dist-info/WHEEL
netcore-0.1.3.dist-info/top_level.txt
netcore-0.1.3.dist-info/RECORD
