Metadata-Version: 2.4
Name: netcore
Version: 0.1.3
Summary: A Network Protocol Framework
Home-page: https://github.com/A03HCY/Netcore
Author: Aiden Hopkins
Author-email: acdphc@qq.com
Classifier: Programming Language :: Python :: 3
Classifier: License :: OSI Approved :: MIT License
Classifier: Operating System :: OS Independent
License-File: LICENSE
Dynamic: author
Dynamic: author-email
Dynamic: classifier
Dynamic: description
Dynamic: description-content-type
Dynamic: home-page
Dynamic: license-file
Dynamic: summary
